[{"vid":"1071","uid":"1","title":"Benefits of OSH and cost of poor OSH","log":"","status":"1","comment":"1","promote":"0","sticky":"0","vuuid":"0a9acb89-6af8-4470-b5be-f55ceaf04a5f","nid":"1068","type":"article","language":"en","created":"1409929958","changed":"1409931517","tnid":"0","translate":"0","uuid":"fd81ac64-3deb-4118-b4aa-b499e0e2e576","revision_timestamp":"1409931517","revision_uid":"1","body":{"en":[{"value":"\u003Cdiv class=\u0022wysiwyg_accordion\u0022\u003E\u003Ch3\u003EThe big picture\u003C\/h3\u003E\u003Cp class=\u0022Textfo\u0022\u003EEveryone from individual workers to national health systems loses out when OSH is neglected. But this means that everyone can benefit from better policies and practices.\u003C\/p\u003E\u003Cp class=\u0022Textfo\u0022\u003ECountries with poor workplace safety and health systems use valuable resources dealing with avoidable injuries and illnesses. A strong national strategy leads to numerous benefits, such as:\u003C\/p\u003E\u003Cul\u003E\u003Cli\u003Eimproved productivity through less sickness absence\u003C\/li\u003E\u003Cli\u003Ecutting healthcare costs\u003C\/li\u003E\u003Cli\u003Ekeeping older workers in employment\u003C\/li\u003E\u003Cli\u003Estimulating more efficient working methods and technologies\u003C\/li\u003E\u003Cli\u003Ereducing the number of people who have to cut their hours to care for a family member\u003C\/li\u003E\u003C\/ul\u003E\u003Ch3\u003EGetting a clearer view\u003C\/h3\u003E\u003Cp class=\u0022Textfo\u0022\u003EIt\u2019s vital that policy-makers understand the costs of poor or non-existent OSH. Some are obvious \u2014 lost working days and compensation payments, for example. Some, though, are harder to estimate, such as the cost for human suffering. The economic effects on society of workplace accidents and work-related injuries can be hidden, like lower staff morale or lost clients and contracts.\u003C\/p\u003E\u003Cp class=\u0022Textfo\u0022\u003EEstimates vary \u2014 which is one reason why more research is needed \u2014 but typically, for most countries, the costs of accidents at work and occupational ill health range from 2.6% to 3.8% of GDP.\u003C\/p\u003E\u003Cp class=\u0022Textfo\u0022\u003EEU-OSHA wants policy-makers to have access to the most accurate figures possible. That\u2019s why we have recently published \u003Ca href=\u0022\/publications\/reports\/executive-summary-estimating-the-cost-of-accidents-and-ill-health-at-work\u0022\u003Ea report comparing the best national studies\u003C\/a\u003E on the costs of poor OSH. The report is the starting point for a large-scale project on estimating the costs of poor OSH across Europe.\u003C\/p\u003E\u003Ch3\u003EThe benefits for business\u003C\/h3\u003E\u003Cp class=\u0022Textfo\u0022\u003ENot only does poor safety and health cost companies money, but good OSH pays dividends. Business with higher safety and health standards are more successful and more sustainable.\u003C\/p\u003E\u003Cp class=\u0022Textfo\u0022\u003EStudies estimate that for every euro invested in OSH, there is a return of 2.2 euros \u003Ca id=\u0022_anchor_1\u0022 name=\u0022_msoanchor_1\u0022 href=\u0022file:\/\/\/I:\/PROJECTS\/Website%20%E2%80%93%20online%20communication\/EU-OSHA%20online%20strategy%202013-2014\/09%20-%20Content%20preparation\/00%20-%20Final%20contents\/Already%20online\/06-Benefits-of-OSH-SEP.docx#_msocom_1\u0022\u003E[link to an external report that keeps on being moved - \u003Cspan style=\u0022font-size: x-large;\u0022\u003ESHALL WE SAVE IT IN OUR WEBSITE????\u003C\/span\u003E\u003C\/a\u003E\u003Ca id=\u0022_anchor_2\u0022 name=\u0022_msoanchor_2\u0022 href=\u0022file:\/\/\/I:\/PROJECTS\/Website%20%E2%80%93%20online%20communication\/EU-OSHA%20online%20strategy%202013-2014\/09%20-%20Content%20preparation\/00%20-%20Final%20contents\/Already%20online\/06-Benefits-of-OSH-SEP.docx#_msocom_2\u0022\u003E]\u003C\/a\u003E\u0026nbsp;and that the cost\u2013benefit ratio of improving safety and health is favourable\u003C\/p\u003E\u003Cp class=\u0022Textfo\u0022\u003EThe costs of poor OSH can be a particular burden for small enterprises. Our recent report\u0026nbsp;\u003Ca id=\u0022_anchor_1\u0022 style=\u0022line-height: 1.538em;\u0022 name=\u0022_msoanchor_1\u0022 href=\u0022file:\/\/\/I:\/PROJECTS\/Website%20%E2%80%93%20online%20communication\/EU-OSHA%20online%20strategy%202013-2014\/09%20-%20Content%20preparation\/00%20-%20Final%20contents\/Already%20online\/06-Benefits-of-OSH-SEP.docx#_msocom_1\u0022\u003E[STILL TO BE PUBLISHED\u003C\/a\u003E\u003Ca id=\u0022_anchor_2\u0022 style=\u0022line-height: 1.538em;\u0022 name=\u0022_msoanchor_2\u0022 href=\u0022file:\/\/\/I:\/PROJECTS\/Website%20%E2%80%93%20online%20communication\/EU-OSHA%20online%20strategy%202013-2014\/09%20-%20Content%20preparation\/00%20-%20Final%20contents\/Already%20online\/06-Benefits-of-OSH-SEP.docx#_msocom_2\u0022\u003E]\u003C\/a\u003E\u003Cspan style=\u0022line-height: 1.538em;\u0022\u003E\u0026nbsp;\u003C\/span\u003E\u003Cspan style=\u0022line-height: 1.538em;\u0022\u003Eshows how good OSH can play a major role enhancing the performance of SMEs\u003C\/span\u003E\u003C\/p\u003E\u003Cp class=\u0022Textfo\u0022\u003EThe economic advantages of good OSH for businesses large and small are significant. To give just a few examples, good workplace safety and health:\u003C\/p\u003E\u003Cul\u003E\u003Cli\u003Eimproves workers\u2019 productivity\u003C\/li\u003E\u003Cli\u003Ecuts down on absenteeism\u003C\/li\u003E\u003Cli\u003Ereduces compensation payments\u003C\/li\u003E\u003Cli\u003Emeets the requirements of public and private sector contractors\u003C\/li\u003E\u003C\/ul\u003E\u003Cp class=\u0022Textfo\u0022\u003ETaking action could bring significant benefits to your business. Find out more about \u003Ca href=\u0022node\/570\u0022\u003Eimplementing improvements and managing risks\u003C\/a\u003E.\u003C\/p\u003E\u003Ch3\u003EEconomic incentives\u003C\/h3\u003E\u003Cp class=\u0022Textfo\u0022\u003EAcross Europe, schemes have been put in place to reward organisations financially for having safe and healthy workplaces. These include:\u003C\/p\u003E\u003Cul\u003E\u003Cli\u003Elower insurance premiums\u003C\/li\u003E\u003Cli\u003Etax breaks\u003C\/li\u003E\u003Cli\u003Estate subsidies and grants\u003C\/li\u003E\u003C\/ul\u003E\u003Cp class=\u0022Textfo\u0022\u003EOne example is the German butchery sector. Participating companies had their premiums reduced if they promoted safety, for example by buying safety knives or giving safety training to drivers. The scheme resulted in:\u003C\/p\u003E\u003Cul\u003E\u003Cli\u003E1,000 fewer reportable accidents per year for the sector in Germany\u003C\/li\u003E\u003Cli\u003Ea reduction in costs valued at 40\u0026nbsp;million euros in six years\u003C\/li\u003E\u003Cli\u003Ea saving of 4.81 euros for every euro invested\u003C\/li\u003E\u003C\/ul\u003E\u003Cp class=\u0022Textfo\u0022\u003EFor insurers, offering such schemes can help to reduce the number, severity and cost of claims.\u003C\/p\u003E\u003C\/div\u003E\u003Cp class=\u0022Textfo\u0022\u003EFind out more about economic incentives and how they can be introduced:\u003C\/p\u003E\u003Cul\u003E\u003Cli\u003E\u003Ca href=\u0022https:\/\/osha.europa.eu\/en\/publications\/literature_reviews\/guide-economic-incentives\/view?searchterm=\u0022\u003EHow to create economic incentives in occupational safety and health: A practical guide \u003C\/a\u003E\u003C\/li\u003E\u003Cli\u003E\u003Ca href=\u0022https:\/\/osha.europa.eu\/en\/publications\/reports\/economic_incentives_TE3109255ENC\/view?searchterm=\u0022\u003EEconomic incentives to improve occupational safety and health: a review from the European perspective \u003C\/a\u003E\u003C\/li\u003E\u003Cli\u003E\u003Ca href=\u0022http:\/\/oshwiki.eu\/wiki\/External_economic_incentives_for_prevention\u0022\u003EOSHwiki: economic incentives\u003C\/a\u003E\u003C\/li\u003E\u003C\/ul\u003E\u003Cp\u003E\u003Cspan style=\u0022font-size: x-large;\u0022\u003E\u003Cstrong\u003ETHE LAST PARAGRAPH SHOULD DISAPPEAR AS IT WILL BE DISPLAYED \u003C\/strong\u003E\u003C\/span\u003E\u003C\/p\u003E\u003Cp\u003E\u003Cspan style=\u0022font-size: x-large;\u0022\u003E\u003Cstrong\u003EIN THE RIGHT HAND PORTLET, \u003C\/strong\u003E\u003C\/span\u003E\u003C\/p\u003E\u003Cp\u003E\u003Cspan style=\u0022font-size: x-large;\u0022\u003E\u003Cstrong\u003ETO BE CONFIRMED BY PROJECT MANAGER\u003C\/strong\u003E\u003C\/span\u003E\u003C\/p\u003E\u003Cp\u003E\u0026nbsp;\u003C\/p\u003E\u003Cp\u003E\u003Cspan style=\u0022font-size: x-large;\u0022\u003E\u003Cstrong\u003Echeck link to OiRA (migrated content) \u0026gt;\u0026gt;\u0026gt; for BM (or shall we rentranslate?)\u003C\/strong\u003E\u003C\/span\u003E\u003C\/p\u003E\u003Cp\u003E\u0026nbsp;\u003C\/p\u003E","summary":"","format":"full_html","safe_value":"\u003Cdiv class=\u0022wysiwyg_accordion\u0022\u003E\n\u003Ch3\u003EThe big picture\u003C\/h3\u003E\n\u003Cp class=\u0022Textfo\u0022\u003EEveryone from individual workers to national health systems loses out when OSH is neglected. But this means that everyone can benefit from better policies and practices.\u003C\/p\u003E\n\u003Cp class=\u0022Textfo\u0022\u003ECountries with poor workplace safety and health systems use valuable resources dealing with avoidable injuries and illnesses. A strong national strategy leads to numerous benefits, such as:\u003C\/p\u003E\n\u003Cul\u003E\u003Cli\u003Eimproved productivity through less sickness absence\u003C\/li\u003E\n\u003Cli\u003Ecutting healthcare costs\u003C\/li\u003E\n\u003Cli\u003Ekeeping older workers in employment\u003C\/li\u003E\n\u003Cli\u003Estimulating more efficient working methods and technologies\u003C\/li\u003E\n\u003Cli\u003Ereducing the number of people who have to cut their hours to care for a family member\u003C\/li\u003E\n\u003C\/ul\u003E\u003Ch3\u003EGetting a clearer view\u003C\/h3\u003E\n\u003Cp class=\u0022Textfo\u0022\u003EIt\u2019s vital that policy-makers understand the costs of poor or non-existent OSH. Some are obvious \u2014 lost working days and compensation payments, for example. Some, though, are harder to estimate, such as the cost for human suffering. The economic effects on society of workplace accidents and work-related injuries can be hidden, like lower staff morale or lost clients and contracts.\u003C\/p\u003E\n\u003Cp class=\u0022Textfo\u0022\u003EEstimates vary \u2014 which is one reason why more research is needed \u2014 but typically, for most countries, the costs of accidents at work and occupational ill health range from 2.6% to 3.8% of GDP.\u003C\/p\u003E\n\u003Cp class=\u0022Textfo\u0022\u003EEU-OSHA wants policy-makers to have access to the most accurate figures possible. That\u2019s why we have recently published \u003Ca href=\u0022\/publications\/reports\/executive-summary-estimating-the-cost-of-accidents-and-ill-health-at-work\u0022\u003Ea report comparing the best national studies\u003C\/a\u003E on the costs of poor OSH. The report is the starting point for a large-scale project on estimating the costs of poor OSH across Europe.\u003C\/p\u003E\n\u003Ch3\u003EThe benefits for business\u003C\/h3\u003E\n\u003Cp class=\u0022Textfo\u0022\u003ENot only does poor safety and health cost companies money, but good OSH pays dividends. Business with higher safety and health standards are more successful and more sustainable.\u003C\/p\u003E\n\u003Cp class=\u0022Textfo\u0022\u003EStudies estimate that for every euro invested in OSH, there is a return of 2.2 euros \u003Ca id=\u0022_anchor_1\u0022 name=\u0022_msoanchor_1\u0022 href=\u0022file:\/\/\/I:\/PROJECTS\/Website%20%E2%80%93%20online%20communication\/EU-OSHA%20online%20strategy%202013-2014\/09%20-%20Content%20preparation\/00%20-%20Final%20contents\/Already%20online\/06-Benefits-of-OSH-SEP.docx#_msocom_1\u0022\u003E[link to an external report that keeps on being moved - \u003Cspan style=\u0022font-size: x-large;\u0022\u003ESHALL WE SAVE IT IN OUR WEBSITE????\u003C\/span\u003E\u003C\/a\u003E\u003Ca id=\u0022_anchor_2\u0022 name=\u0022_msoanchor_2\u0022 href=\u0022file:\/\/\/I:\/PROJECTS\/Website%20%E2%80%93%20online%20communication\/EU-OSHA%20online%20strategy%202013-2014\/09%20-%20Content%20preparation\/00%20-%20Final%20contents\/Already%20online\/06-Benefits-of-OSH-SEP.docx#_msocom_2\u0022\u003E]\u003C\/a\u003E\u00a0and that the cost\u2013benefit ratio of improving safety and health is favourable\u003C\/p\u003E\n\u003Cp class=\u0022Textfo\u0022\u003EThe costs of poor OSH can be a particular burden for small enterprises. Our recent report\u00a0\u003Ca id=\u0022_anchor_1\u0022 style=\u0022line-height: 1.538em;\u0022 name=\u0022_msoanchor_1\u0022 href=\u0022file:\/\/\/I:\/PROJECTS\/Website%20%E2%80%93%20online%20communication\/EU-OSHA%20online%20strategy%202013-2014\/09%20-%20Content%20preparation\/00%20-%20Final%20contents\/Already%20online\/06-Benefits-of-OSH-SEP.docx#_msocom_1\u0022\u003E[STILL TO BE PUBLISHED\u003C\/a\u003E\u003Ca id=\u0022_anchor_2\u0022 style=\u0022line-height: 1.538em;\u0022 name=\u0022_msoanchor_2\u0022 href=\u0022file:\/\/\/I:\/PROJECTS\/Website%20%E2%80%93%20online%20communication\/EU-OSHA%20online%20strategy%202013-2014\/09%20-%20Content%20preparation\/00%20-%20Final%20contents\/Already%20online\/06-Benefits-of-OSH-SEP.docx#_msocom_2\u0022\u003E]\u003C\/a\u003E\u003Cspan style=\u0022line-height: 1.538em;\u0022\u003E\u00a0\u003C\/span\u003E\u003Cspan style=\u0022line-height: 1.538em;\u0022\u003Eshows how good OSH can play a major role enhancing the performance of SMEs\u003C\/span\u003E\u003C\/p\u003E\n\u003Cp class=\u0022Textfo\u0022\u003EThe economic advantages of good OSH for businesses large and small are significant. To give just a few examples, good workplace safety and health:\u003C\/p\u003E\n\u003Cul\u003E\u003Cli\u003Eimproves workers\u2019 productivity\u003C\/li\u003E\n\u003Cli\u003Ecuts down on absenteeism\u003C\/li\u003E\n\u003Cli\u003Ereduces compensation payments\u003C\/li\u003E\n\u003Cli\u003Emeets the requirements of public and private sector contractors\u003C\/li\u003E\n\u003C\/ul\u003E\u003Cp class=\u0022Textfo\u0022\u003ETaking action could bring significant benefits to your business. Find out more about \u003Ca href=\u0022node\/570\u0022\u003Eimplementing improvements and managing risks\u003C\/a\u003E.\u003C\/p\u003E\n\u003Ch3\u003EEconomic incentives\u003C\/h3\u003E\n\u003Cp class=\u0022Textfo\u0022\u003EAcross Europe, schemes have been put in place to reward organisations financially for having safe and healthy workplaces. These include:\u003C\/p\u003E\n\u003Cul\u003E\u003Cli\u003Elower insurance premiums\u003C\/li\u003E\n\u003Cli\u003Etax breaks\u003C\/li\u003E\n\u003Cli\u003Estate subsidies and grants\u003C\/li\u003E\n\u003C\/ul\u003E\u003Cp class=\u0022Textfo\u0022\u003EOne example is the German butchery sector. Participating companies had their premiums reduced if they promoted safety, for example by buying safety knives or giving safety training to drivers. The scheme resulted in:\u003C\/p\u003E\n\u003Cul\u003E\u003Cli\u003E1,000 fewer reportable accidents per year for the sector in Germany\u003C\/li\u003E\n\u003Cli\u003Ea reduction in costs valued at 40\u00a0million euros in six years\u003C\/li\u003E\n\u003Cli\u003Ea saving of 4.81 euros for every euro invested\u003C\/li\u003E\n\u003C\/ul\u003E\u003Cp class=\u0022Textfo\u0022\u003EFor insurers, offering such schemes can help to reduce the number, severity and cost of claims.\u003C\/p\u003E\n\u003C\/div\u003E\n\u003Cp class=\u0022Textfo\u0022\u003EFind out more about economic incentives and how they can be introduced:\u003C\/p\u003E\n\u003Cul\u003E\u003Cli\u003E\u003Ca href=\u0022https:\/\/osha.europa.eu\/en\/publications\/literature_reviews\/guide-economic-incentives\/view?searchterm=\u0022\u003EHow to create economic incentives in occupational safety and health: A practical guide \u003C\/a\u003E\u003C\/li\u003E\n\u003Cli\u003E\u003Ca href=\u0022https:\/\/osha.europa.eu\/en\/publications\/reports\/economic_incentives_TE3109255ENC\/view?searchterm=\u0022\u003EEconomic incentives to improve occupational safety and health: a review from the European perspective \u003C\/a\u003E\u003C\/li\u003E\n\u003Cli\u003E\u003Ca href=\u0022http:\/\/oshwiki.eu\/wiki\/External_economic_incentives_for_prevention\u0022\u003EOSHwiki: economic incentives\u003C\/a\u003E\u003C\/li\u003E\n\u003C\/ul\u003E\u003Cp\u003E\u003Cspan style=\u0022font-size: x-large;\u0022\u003E\u003Cstrong\u003ETHE LAST PARAGRAPH SHOULD DISAPPEAR AS IT WILL BE DISPLAYED \u003C\/strong\u003E\u003C\/span\u003E\u003C\/p\u003E\n\u003Cp\u003E\u003Cspan style=\u0022font-size: x-large;\u0022\u003E\u003Cstrong\u003EIN THE RIGHT HAND PORTLET, \u003C\/strong\u003E\u003C\/span\u003E\u003C\/p\u003E\n\u003Cp\u003E\u003Cspan style=\u0022font-size: x-large;\u0022\u003E\u003Cstrong\u003ETO BE CONFIRMED BY PROJECT MANAGER\u003C\/strong\u003E\u003C\/span\u003E\u003C\/p\u003E\n\u003Cp\u003E\u00a0\u003C\/p\u003E\n\u003Cp\u003E\u003Cspan style=\u0022font-size: x-large;\u0022\u003E\u003Cstrong\u003Echeck link to OiRA (migrated content) \u0026gt;\u0026gt;\u0026gt; for BM (or shall we rentranslate?)\u003C\/strong\u003E\u003C\/span\u003E\u003C\/p\u003E\n\u003Cp\u003E\u00a0\u003C\/p\u003E\n","safe_summary":""}]},"field_tags":[],"field_image":[],"title_field":{"en":[{"value":"Benefits of OSH and cost of poor OSH","format":null,"safe_value":"Benefits of OSH and cost of poor OSH"}]},"field_activity":[],"field_nace_codes":[],"field_project_manager":[],"field_publication_date":{"und":[{"value":"2014-09-05 00:00:00","timezone":"UTC","timezone_db":"UTC","date_type":"datetime"}]},"field_section":[],"field_summary":{"en":[{"value":"In tough economic times, it\u2019s important to remember that poor workplace safety and health costs money. What\u2019s more, case studies show that good OSH management in a business is linked to improved performance and profitability. ","format":null,"safe_value":"In tough economic times, it\u2019s important to remember that poor workplace safety and health costs money. What\u2019s more, case studies show that good OSH management in a business is linked to improved performance and profitability. "}]},"field_thesaurus":[],"field_workflow_status":[],"title_original":"Benefits of OSH and cost of poor OSH","translations":{"original":"en","data":{"en":{"entity_type":"node","entity_id":"1068","language":"en","source":"","uid":"1","status":"1","translate":"0","created":"1409929958","changed":"1409931517"}},"#node_export_object":"1"},"metatags":[],"rdf_mapping":{"field_image":{"predicates":["og:image","rdfs:seeAlso"],"type":"rel"},"field_tags":{"predicates":["dc:subject"],"type":"rel"},"rdftype":["sioc:Item","foaf:Document"],"title":{"predicates":["dc:title"]},"created":{"predicates":["dc:date","dc:created"],"datatype":"xsd:dateTime","callback":"date_iso8601"},"changed":{"predicates":["dc:modified"],"datatype":"xsd:dateTime","callback":"date_iso8601"},"body":{"predicates":["content:encoded"]},"uid":{"predicates":["sioc:has_creator"],"type":"rel"},"name":{"predicates":["foaf:name"]},"comment_count":{"predicates":["sioc:num_replies"],"datatype":"xsd:integer"},"last_activity":{"predicates":["sioc:last_activity_date"],"datatype":"xsd:dateTime","callback":"date_iso8601"}},"cid":"0","last_comment_timestamp":"1409929958","last_comment_name":null,"last_comment_uid":"1","comment_count":"0","name":"admin","picture":"0","data":"b:0;","path":{"pid":"26184","source":"node\/1068","alias":"articles\/benefits-osh-and-cost-poor-osh","language":"en"},"menu":{"link_title":"Benefits of OSH","mlid":0,"plid":"537","menu_name":"main-menu","weight":"-49","options":[],"module":"menu","expanded":"1","hidden":"0","has_children":"0","customized":0,"parent_depth_limit":8,"description":"","enabled":1},"node_export_drupal_version":"7","#node_export_object":"1"}]